reconfigure/__init__.py
reconfigure/nodes.py
reconfigure/builders/__init__.py
reconfigure/builders/base.py
reconfigure/builders/bound.py
reconfigure/builders/bound_tests.py
reconfigure/configs/__init__.py
reconfigure/configs/ajenti.py
reconfigure/configs/base.py
reconfigure/configs/bind9.py
reconfigure/configs/crontab.py
reconfigure/configs/csf.py
reconfigure/configs/ctdb.py
reconfigure/configs/dhcpd.py
reconfigure/configs/exports.py
reconfigure/configs/fstab.py
reconfigure/configs/group.py
reconfigure/configs/hosts.py
reconfigure/configs/iptables.py
reconfigure/configs/netatalk.py
reconfigure/configs/nsd.py
reconfigure/configs/passwd.py
reconfigure/configs/resolv.py
reconfigure/configs/samba.py
reconfigure/configs/squid.py
reconfigure/configs/supervisor.py
reconfigure/includers/__init__.py
reconfigure/includers/auto.py
reconfigure/includers/base.py
reconfigure/includers/bind9.py
reconfigure/includers/nginx.py
reconfigure/includers/supervisor.py
reconfigure/items/__init__.py
reconfigure/items/ajenti.py
reconfigure/items/bind9.py
reconfigure/items/bound.py
reconfigure/items/crontab.py
reconfigure/items/csf.py
reconfigure/items/ctdb.py
reconfigure/items/dhcpd.py
reconfigure/items/exports.py
reconfigure/items/fstab.py
reconfigure/items/group.py
reconfigure/items/hosts.py
reconfigure/items/iptables.py
reconfigure/items/netatalk.py
reconfigure/items/nsd.py
reconfigure/items/passwd.py
reconfigure/items/resolv.py
reconfigure/items/samba.py
reconfigure/items/squid.py
reconfigure/items/supervisor.py
reconfigure/items/util.py
reconfigure/parsers/__init__.py
reconfigure/parsers/base.py
reconfigure/parsers/bind9.py
reconfigure/parsers/crontab.py
reconfigure/parsers/exports.py
reconfigure/parsers/ini.py
reconfigure/parsers/iptables.py
reconfigure/parsers/jsonparser.py
reconfigure/parsers/nginx.py
reconfigure/parsers/nsd.py
reconfigure/parsers/shell.py
reconfigure/parsers/squid.py
reconfigure/parsers/ssv.py
reconfigure-0.1.81.dist-info/DESCRIPTION.rst
reconfigure-0.1.81.dist-info/METADATA
reconfigure-0.1.81.dist-info/RECORD
reconfigure-0.1.81.dist-info/WHEEL
reconfigure-0.1.81.dist-info/metadata.json
reconfigure-0.1.81.dist-info/top_level.txt
