Metadata-Version: 2.0
Name: reconfigure
Version: 0.1.81
Summary: An ORM for config files
Home-page: http://ajenti.org/
Author: Eugeny Pankov
Author-email: e@ajenti.org
License: LGPLv3
Platform: UNKNOWN
Classifier: License :: OSI Approved :: GNU Lesser General Public License v3 (LGPLv3)
Requires-Dist: chardet
